topasdosecalc/__init__.py
topasdosecalc/__main__.py
topasdosecalc/topasdosecalc.py
topasdosecalc/src/__init__.py
topasdosecalc/src/config.py
topasdosecalc/src/dcm.ico
topasdosecalc/src/folder.ico
topasdosecalc/src/icon.png
topasdosecalc/src/merge_doses.py
topasdosecalc/src/output.py
topasdosecalc/src/structure_selector.py
topasdosecalc/src/topas.ico
topasdosecalc/src/Azure-ttk-theme/.git
topasdosecalc/src/Azure-ttk-theme/.gitignore
topasdosecalc/src/Azure-ttk-theme/Dark screenshot.png
topasdosecalc/src/Azure-ttk-theme/LICENSE
topasdosecalc/src/Azure-ttk-theme/Light screenshot.png
topasdosecalc/src/Azure-ttk-theme/README.md
topasdosecalc/src/Azure-ttk-theme/azure.tcl
topasdosecalc/src/Azure-ttk-theme/example.py
topasdosecalc/src/Azure-ttk-theme/screenshot.png
topasdosecalc/src/Azure-ttk-theme/theme/dark.tcl
topasdosecalc/src/Azure-ttk-theme/theme/light.tcl
topasdosecalc/src/Azure-ttk-theme/theme/dark/box-accent.png
topasdosecalc/src/Azure-ttk-theme/theme/dark/box-basic.png
topasdosecalc/src/Azure-ttk-theme/theme/dark/box-hover.png
topasdosecalc/src/Azure-ttk-theme/theme/dark/box-invalid.png
topasdosecalc/src/Azure-ttk-theme/theme/dark/button-hover.png
topasdosecalc/src/Azure-ttk-theme/theme/dark/card.png
topasdosecalc/src/Azure-ttk-theme/theme/dark/check-accent.png
topasdosecalc/src/Azure-ttk-theme/theme/dark/check-basic.png
topasdosecalc/src/Azure-ttk-theme/theme/dark/check-hover.png
topasdosecalc/src/Azure-ttk-theme/theme/dark/check-tri-accent.png
topasdosecalc/src/Azure-ttk-theme/theme/dark/check-tri-basic.png
topasdosecalc/src/Azure-ttk-theme/theme/dark/check-tri-hover.png
topasdosecalc/src/Azure-ttk-theme/theme/dark/circle-accent.png
topasdosecalc/src/Azure-ttk-theme/theme/dark/circle-basic.png
topasdosecalc/src/Azure-ttk-theme/theme/dark/circle-hover.png
topasdosecalc/src/Azure-ttk-theme/theme/dark/combo-button-basic.png
topasdosecalc/src/Azure-ttk-theme/theme/dark/combo-button-focus.png
topasdosecalc/src/Azure-ttk-theme/theme/dark/combo-button-hover.png
topasdosecalc-1.4.dist-info/LICENSE
topasdosecalc-1.4.dist-info/METADATA
topasdosecalc-1.4.dist-info/WHEEL
topasdosecalc-1.4.dist-info/entry_points.txt
topasdosecalc-1.4.dist-info/top_level.txt
topasdosecalc-1.4.dist-info/RECORD
