Metadata-Version: 2.1
Name: topasdosecalc
Version: 1.4
Summary: Merge and scale TOPAS DICOMS - calculate and compare DVHs
Home-page: https://github.com/sebasj13/TopasDoseCalc
Author: Sebastian Schäfer
Author-email: sebastian.schaefer@student.uni-halle.de
Project-URL: Bug Tracker, https://github.com/sebasj13/TopasDoseCalc/issues
Keywords: topas,monte-carlo,python,simulation,dvh,dicom
Classifier: Programming Language :: Python :: 3
Classifier: License :: OSI Approved :: MIT License
Classifier: Operating System :: OS Independent
Requires-Python: >=3.8
License-File: LICENSE
Requires-Dist: numpy
Requires-Dist: matplotlib
Requires-Dist: topas2numpy
Requires-Dist: pydicom
Requires-Dist: dicompyler-core
Requires-Dist: natsort
Requires-Dist: Pillow
